heroku_tl_new-3.4.9.dist-info/licenses/LICENSE.md
herokutl/__init__.py
herokutl/custom.py
herokutl/functions.py
herokutl/helpers.py
herokutl/hints.py
herokutl/password.py
herokutl/requestiter.py
herokutl/sync.py
herokutl/types.py
herokutl/utils.py
herokutl/version.py
herokutl/_updates/__init__.py
herokutl/_updates/entitycache.py
herokutl/_updates/messagebox.py
herokutl/_updates/session.py
herokutl/client/__init__.py
herokutl/client/account.py
herokutl/client/auth.py
herokutl/client/bots.py
herokutl/client/buttons.py
herokutl/client/chats.py
herokutl/client/dialogs.py
herokutl/client/downloads.py
herokutl/client/messageparse.py
herokutl/client/messages.py
herokutl/client/telegrambaseclient.py
herokutl/client/telegramclient.py
herokutl/client/updates.py
herokutl/client/uploads.py
herokutl/client/users.py
herokutl/crypto/__init__.py
herokutl/crypto/aes.py
herokutl/crypto/aesctr.py
herokutl/crypto/authkey.py
herokutl/crypto/cdndecrypter.py
herokutl/crypto/factorization.py
herokutl/crypto/libssl.py
herokutl/crypto/rsa.py
herokutl/errors/__init__.py
herokutl/errors/common.py
herokutl/errors/rpcbaseerrors.py
herokutl/errors/rpcerrorlist.py
herokutl/events/__init__.py
herokutl/events/album.py
herokutl/events/callbackquery.py
herokutl/events/chataction.py
herokutl/events/common.py
herokutl/events/inlinequery.py
herokutl/events/messagedeleted.py
herokutl/events/messageedited.py
herokutl/events/messageread.py
herokutl/events/newmessage.py
herokutl/events/raw.py
herokutl/events/userupdate.py
herokutl/extensions/__init__.py
herokutl/extensions/binaryreader.py
herokutl/extensions/html.py
herokutl/extensions/markdown.py
herokutl/extensions/messagepacker.py
herokutl/network/__init__.py
herokutl/network/authenticator.py
herokutl/network/mtprotoplainsender.py
herokutl/network/mtprotosender.py
herokutl/network/mtprotostate.py
herokutl/network/requeststate.py
herokutl/network/connection/__init__.py
herokutl/network/connection/connection.py
herokutl/network/connection/http.py
herokutl/network/connection/tcpabridged.py
heroku_tl_new-3.4.9.dist-info/METADATA
heroku_tl_new-3.4.9.dist-info/WHEEL
heroku_tl_new-3.4.9.dist-info/top_level.txt
heroku_tl_new-3.4.9.dist-info/RECORD
