Metadata-Version: 2.4
Name: heroku-tl-new
Version: 3.4.9
Summary: This library is built for the Heroku userbot and is based on Telethon.
Home-page: https://github.com/coddrago/heroku-tl
Download-URL: https://pypi.org/project/heroku-tl-new/
Author: Codrago
Author-email: codrago@codwiz.ru
License: CCBYNCND V4
Keywords: telegram api chat client library messaging mtproto
Classifier: Development Status :: 5 - Production/Stable
Classifier: Intended Audience :: Developers
Classifier: Topic :: Communications :: Chat
Classifier: License :: OSI Approved :: MIT License
Classifier: Programming Language :: Python :: 3
Classifier: Programming Language :: Python :: 3.5
Classifier: Programming Language :: Python :: 3.6
Classifier: Programming Language :: Python :: 3.7
Classifier: Programming Language :: Python :: 3.8
Requires-Python: >=3.5
License-File: LICENSE.md
Requires-Dist: pyaes
Requires-Dist: rsa
Requires-Dist: aiofile==3.8.1
Requires-Dist: aiofiles==24.1.0
Requires-Dist: gitpython==3.1.27
Requires-Dist: meval==2.5
Requires-Dist: aiohttp_jinja2==1.5
Requires-Dist: aiohttp==3.8.3
Requires-Dist: Jinja2==3.1.2
Requires-Dist: requests==2.27.1
Requires-Dist: aiogram==2.25
Requires-Dist: grapheme==0.6.0
Requires-Dist: emoji==2.1.0
Requires-Dist: werkzeug==3.1.0
Requires-Dist: psutil==6.0.0
Requires-Dist: tgcrypto==1.2.5
Requires-Dist: rsa==4.9
Requires-Dist: ruamel.yaml==0.17.21
Requires-Dist: bs4==0.0.2
Provides-Extra: cryptg
Requires-Dist: cryptg; extra == "cryptg"
Dynamic: author
Dynamic: author-email
Dynamic: classifier
Dynamic: description
Dynamic: description-content-type
Dynamic: download-url
Dynamic: home-page
Dynamic: keywords
Dynamic: license
Dynamic: license-file
Dynamic: provides-extra
Dynamic: requires-dist
Dynamic: requires-python
Dynamic: summary
